stringcompare/__init__.py
stringcompare/functions/__init__.py
stringcompare/functions/create_chart.py
stringcompare/functions/generate_data.py
stringcompare/functions/hashing_search.py
stringcompare/functions/linear_search.py
stringcompare/functions/measure_time.py
stringcompare/functions/stringcompare.py
stringcompare/functions/unit_tests.py
stringcompare/stringcompare.py
stringcompare/unit_tests.py
stringcompare-0.1.11.dist-info/entry_points.txt
stringcompare-0.1.11.dist-info/WHEEL
stringcompare-0.1.11.dist-info/METADATA
stringcompare-0.1.11.dist-info/RECORD
